ssc/__init__.py
ssc/plotting/__init__.py
ssc/plotting/violin.py
ssc_python-0.1.0.dist-info/licenses/LICENSE
ssc_python-0.1.0.dist-info/METADATA
ssc_python-0.1.0.dist-info/WHEEL
ssc_python-0.1.0.dist-info/top_level.txt
ssc_python-0.1.0.dist-info/RECORD
