Metadata-Version: 2.4
Name: ssc-python
Version: 0.1.0
Summary: Signaling Single Cell - Visualizations for single-cell RNA sequencing data
Author-email: Wei-Che Ko <your.email@example.com>
License: MIT
Project-URL: Homepage, https://github.com/yourusername/ssc
Project-URL: Bug Reports, https://github.com/yourusername/ssc/issues
Project-URL: Source, https://github.com/yourusername/ssc
Classifier: Development Status :: 3 - Alpha
Classifier: Intended Audience :: Science/Research
Classifier: License :: OSI Approved :: MIT License
Classifier: Programming Language :: Python :: 3
Classifier: Programming Language :: Python :: 3.8
Classifier: Programming Language :: Python :: 3.9
Classifier: Programming Language :: Python :: 3.10
Classifier: Programming Language :: Python :: 3.11
Classifier: Topic :: Scientific/Engineering :: Bio-Informatics
Requires-Python: >=3.8
License-File: LICENSE
Requires-Dist: pandas>=1.3.0
Requires-Dist: numpy>=1.20.0
Requires-Dist: matplotlib>=3.5.0
Requires-Dist: seaborn>=0.11.0
Requires-Dist: scanpy>=1.8.0
Provides-Extra: dev
Requires-Dist: pytest>=6.0; extra == "dev"
Requires-Dist: black; extra == "dev"
Requires-Dist: isort; extra == "dev"
Requires-Dist: flake8; extra == "dev"
Dynamic: license-file
